{
  "company": {
    "name": "為福樓",
    "phone": "0227888686",
    "description": "港式燒臘便當",
    "minOrderNum": 5,
    "minOrderMoney": 600,
    "orderBefore": "10:36 AM"
  },
  "menu": [
    {
      "name": "玫瑰油雞腿飯",
      "price": 170
    },
    {
      "name": "燒鴨腿飯",
      "price": 170
    },
    {
      "name": "三寶飯",
      "price": 130
    },
    {
      "name": "蜜汁燒雞腿飯",
      "price": 130
    },
    {
      "name": "臘味飯",
      "price": 120
    },
    {
      "name": "叉燒燒肉飯",
      "price": 120
    },
    {
      "name": "燒鴨叉燒飯",
      "price": 120
    },
    {
      "name": "燒鴨叉燒飯",
      "price": 120
    },
    {
      "name": "燒鴨油雞飯",
      "price": 120
    },
    {
      "name": "燒鴨燒肉飯",
      "price": 120
    },
    {
      "name": "油雞叉燒飯",
      "price": 120
    },
    {
      "name": "油雞燒肉飯",
      "price": 120
    },
    {
      "name": "肝腸飯",
      "price": 120
    },
    {
      "name": "臘腸飯",
      "price": 120
    },
    {
      "name": "脆皮燒肉飯",
      "price": 120
    },
    {
      "name": "玫瑰油雞飯",
      "price": 120
    },
    {
      "name": "脆皮燒鴨飯",
      "price": 120
    },
    {
      "name": "脆皮燒肉飯",
      "price": 120
    },
    {
      "name": "玫瑰油雞飯",
      "price": 110
    },
    {
      "name": "脆皮燒鴨飯",
      "price": 110
    },
    {
      "name": "蜜汁叉燒飯",
      "price": 110
    },
    {
      "name": "肉絲炒飯",
      "price": 135
    },
    {
      "name": "蝦仁炒飯",
      "price": 135
    },
    {
      "name": "牛肉炒飯",
      "price": 135
    },
    {
      "name": "鳳梨炒飯",
      "price": 135
    },
    {
      "name": "三鮮炒麵",
      "price": 135
    },
    {
      "name": "牛肉炒麵",
      "price": 135
    },
    {
      "name": "木須炒麵",
      "price": 135
    },
    {
      "name": "三鮮燴飯",
      "price": 135
    },
    {
      "name": "牛肉燴飯",
      "price": 135
    },
    {
      "name": "羊肉燴飯",
      "price": 135
    }
  ]
}
